Práctica 2/Codigo_Practica2/componentes.v
//Componentes varios

//Banco de registros de dos salidas y una entrada
module regfile(input  wire        clk, 
               input  wire        we3,           //señal de habilitación de escritura
               input  wire [3:0]  ra1, ra2, wa3, //valores de regs leidos y reg a escribir
               input  wire [7:0]  wd3, 			 //dato a escribir
               output wire [7:0]  rd1, rd2);     //salida de datos leidos

  reg [7:0] regb[0:15]; //memoria de 16 registros de 8 bits de ancho
  
  //assign regb[0] = 0;
  
  // El registro 0 siempre es cero
  // se leen dos reg combinacionalmente
  // y la escritura del tercero ocurre en flanco de subida del reloj
  always @(posedge clk)
    if (we3) regb[wa3] <= wd3;	
  
  assign rd1 = (ra1 != 0) ? regb[ra1] : 0;
  assign rd2 = (ra2 != 0) ? regb[ra2] : 0;
endmodule

//modulo sumador  
module sum(input  wire [9:0] a, b,
             output wire [9:0] y);

  assign y = a + b;
endmodule

//modulo de registro para modelar el PC, cambia en cada flanco de subida de reloj o de reset
module registro #(parameter WIDTH = 8)
              (input  wire             clk, reset,
               input  wire [WIDTH-1:0] d, 
               output reg  [WIDTH-1:0] q);

  always @(posedge clk, posedge reset)
    if (reset) q <= 0;
    else       q <= d;
endmodule

//modulo multiplexor, cos s=1 sale d1, s=0 sale d0
module mux2 #(parameter WIDTH = 8)
             (input  wire [WIDTH-1:0] d0, d1, 
              input  wire             s, 
              output wire [WIDTH-1:0] y);

  assign y = s ? d1 : d0; 
endmodule

Práctica 2/Codigo_Practica2/alu.v
module alu(input wire [7:0] a, b,
           input wire [2:0] op,
           output wire [7:0] y,
           output wire zero);

reg [7:0] s;		   
		   
		   
always @(a, b, op)
begin
  case (op)              
    3'b000: s = a;
    3'b001: s = ~a;
    3'b010: s = a + b;
    3'b011: s = a - b;
    3'b100: s = a & b;
    3'b101: s = a | b;
    3'b110: s = -a;
    3'b111: s = -b;
	default: s = 'bx; //desconocido en cualquier otro caso (x ó z), por si se modifica el código
  endcase
end

assign y = s;

//Calculo del flag de cero

assign zero = ~(|y);   //operador de reducción |y hace la or de los bits del vector 'y' y devuelve 1 bit resultado
	
 
endmodule

Práctica 2/Codigo_Practica2/memprog.v
//Memoria de programa

module memprog(input wire clk,
               input wire [9:0] a,
               output wire [15:0] rd);

   reg [15:0] mem[0:1023]; //memoria de 1024 palabras de 16 bits de ancho

   initial
      begin
        $readmemb("progfile.dat",mem); // inicializa la memoria del fichero en texto binario
      end

   assign rd = mem[a];

endmodule

Práctica 2/Codigo_Practica2/microc.v
`include "componentes.v"
`include "alu.v"
`include "memprog.v"

module microc(input wire clk, reset, s_inc, s_inm, we3, input wire [2:0] op, output wire z, output wire [5:0] opcode);
//Microcontrolador sin memoria de datos de un solo ciclo

wire [9:0] ePC;
wire [9:0] ssum;//salida del sumador
wire [9:0] sPC;//salida PC
wire [15:0] smem;//salida memoria
wire [7:0] srd1;
wire [7:0] srd2;
wire [7:0] salu;
wire [7:0] wd3;
//Instanciar e interconectar pc, memprog, regfile, alu, sum y mux's



registro #10 PC(clk,reset,ePC,sPC);
memprog mem_(clk,sPC,smem);
regfile banco(clk,we3,smem[7:4],smem[11:8],smem[15:12],wd3,srd1,srd2);
alu alu_ (srd1,srd2,op,salu,z);
sum sumador(sPC,1'b1,ssum);

mux2 #(10) mux2_1(smem[15:6],ssum,s_inc,ePC);//Sumador del PC 
mux2 #(8) mux2_2(salu,smem[11:4],s_inm,wd3);//Entrada banco registros

assign opcode = smem[5:0];
endmodule

Práctica 2/Codigo_Practica2/uc.v
module uc (input wire clk, reset, z, input wire [5:0] opcode, output reg s_inc, s_inm, we3,fin , output reg [2:0] op);//Cambiams wire por reg



always @( * )//Posible fallo al no incluir reset
	
	casex (opcode)

		6'bxx0xxx://ALU
			begin
				we3 <= 1'b1;//Activar escritura				
				op=opcode[2:0];
				s_inc <= 1'b1; //Incrementa PC
				s_inm <= 1'b0; //Salida sumador a banco de registro				
			end

		6'bxx1000://CARGA
			begin
				s_inc <= 1'b1; //Suma uno a PC
				s_inm <= 1'b1; //WA3 a banco de registro y Dato inmediato a WD3
				we3 <=1'b1; //Habilitar escritura
			end

		6'bxx1001://SALTO ABSOLUTO
			begin
				s_inc <= 1'b0; // Direccion a PC
				s_inm <= 1'b0; //No tiene importancia
				we3 <= 1'b0; //No se escribe
			end

		6'bxx1010://SALTO CONDICIONAL 0
			begin
				s_inm <= 1'b0;
				we3 <= 1'b0;			
				if (z)				// 1 -> resultado op anterior 0
					s_inc <= 1'b0; //Salto a la instruccion en registro de direccion
				else
					s_inc <= 1'b1; //Salto a la siguiente instruccion
			end

		6'bxx1011://SALTO CONDICIONAL no 0
			begin
				s_inm <= 1'b0;
				we3 <= 1'b0;
				if (z)				
					s_inc <= 1'b1; //Siguiente instruccion
				else
					s_inc <= 1'b0; //Salto a la siguiente
			end
/*
		6'bxx1100://SALTO RELATIVO
			begin
				we3 <=1'b0					
				op=opcode[2:0];
				s_inc <=
				s_inm <=				
			end
*/		6'bxx1111://Halt
			begin
				fin <= 1'b1;							
			end
	endcase

endmodule

Práctica 2/Codigo_Practica2/procesador.v
`include "uc.v"
`include "microc.v"

module procesador(input wire clk, reset, output wire z, s_inc, s_inm, we3,fin,output wire [2:0] op,output wire [5:0] opcode);

/*wire z,s_inc,s_inm,we3;
wire [2:0] op;*/


uc uc_ (clk, reset, z,opcode, s_inc, s_inm, we3,fin , op);
microc microc_(clk, reset, s_inc, s_inm, we3, op, z, opcode);



endmodule

Práctica 2/Codigo_Practica2/procesador_tb.v
`timescale 1 ns / 10 ps
`include "procesador.v"

module procesador_tb;
reg t_clk, t_reset;
wire t_s_inc, t_s_inm,t_we3, t_z, t_fin;
wire [2:0] t_op;
wire [5:0] t_opcode;

procesador intel(t_clk,t_reset,t_z,t_s_inc,t_s_inm,t_we3,t_fin,t_op,t_opcode);
always //siempre activo, no hay condición de activación
begin
	if(t_fin)
		t_clk = 0;
	else
		begin
		t_clk = 1;
		#5;
		t_clk = 0;
		#5;
		end
end

initial
begin
  $monitor();
  $dumpfile("intel.vcd");
  $dumpvars;	
	t_reset = 1'b1;
	#5;
	t_reset = 1'b0;
	#800;
  $finish;
end
endmodule

Práctica 2/Codigo_Practica2/intel.vcd
$date
	Thu Feb 28 20:02:30 2013
$end
$version
	Icarus Verilog
$end
$timescale
	10ps
$end
$scope module procesador_tb $end
$var wire 1 ! t_fin $end
$var wire 3 " t_op [2:0] $end
$var wire 6 # t_opcode [5:0] $end
$var wire 1 $ t_s_inc $end
$var wire 1 % t_s_inm $end
$var wire 1 & t_we3 $end
$var wire 1 ' t_z $end
$var reg 1 ( t_clk $end
$var reg 1 ) t_reset $end
$scope module intel $end
$var wire 1 * clk $end
$var wire 1 ! fin $end
$var wire 3 + op [2:0] $end
$var wire 6 , opcode [5:0] $end
$var wire 1 - reset $end
$var wire 1 $ s_inc $end
$var wire 1 % s_inm $end
$var wire 1 & we3 $end
$var wire 1 ' z $end
$scope module uc_ $end
$var wire 1 * clk $end
$var wire 6 . opcode [5:0] $end
$var wire 1 - reset $end
$var wire 1 ' z $end
$var reg 1 / fin $end
$var reg 3 0 op [2:0] $end
$var reg 1 1 s_inc $end
$var reg 1 2 s_inm $end
$var reg 1 3 we3 $end
$upscope $end
$scope module microc_ $end
$var wire 1 * clk $end
$var wire 10 4 ePC [9:0] $end
$var wire 3 5 op [2:0] $end
$var wire 6 6 opcode [5:0] $end
$var wire 1 - reset $end
$var wire 10 7 sPC [9:0] $end
$var wire 1 $ s_inc $end
$var wire 1 % s_inm $end
$var wire 8 8 salu [7:0] $end
$var wire 16 9 smem [15:0] $end
$var wire 8 : srd1 [7:0] $end
$var wire 8 ; srd2 [7:0] $end
$var wire 10 < ssum [9:0] $end
$var wire 8 = wd3 [7:0] $end
$var wire 1 & we3 $end
$var wire 1 ' z $end
$scope module PC $end
$var wire 1 * clk $end
$var wire 10 > d [9:0] $end
$var wire 1 - reset $end
$var reg 10 ? q [9:0] $end
$upscope $end
$scope module mem_ $end
$var wire 10 @ a [9:0] $end
$var wire 1 * clk $end
$var wire 16 A rd [15:0] $end
$upscope $end
$scope module banco $end
$var wire 1 * clk $end
$var wire 4 B ra1 [3:0] $end
$var wire 4 C ra2 [3:0] $end
$var wire 8 D rd1 [7:0] $end
$var wire 8 E rd2 [7:0] $end
$var wire 4 F wa3 [3:0] $end
$var wire 8 G wd3 [7:0] $end
$var wire 1 & we3 $end
$upscope $end
$scope module alu_ $end
$var wire 8 H a [7:0] $end
$var wire 8 I b [7:0] $end
$var wire 3 J op [2:0] $end
$var wire 8 K y [7:0] $end
$var wire 1 ' zero $end
$var reg 8 L s [7:0] $end
$upscope $end
$scope module sumador $end
$var wire 10 M a [9:0] $end
$var wire 10 N b [9:0] $end
$var wire 10 O y [9:0] $end
$upscope $end
$scope module mux2_1 $end
$var wire 10 P d0 [9:0] $end
$var wire 10 Q d1 [9:0] $end
$var wire 1 $ s $end
$var wire 10 R y [9:0] $end
$upscope $end
$scope module mux2_2 $end
$var wire 8 S d0 [7:0] $end
$var wire 8 T d1 [7:0] $end
$var wire 1 % s $end
$var wire 8 U y [7:0] $end
$upscope $end
$upscope $end
$upscope $end
$upscope $end
$enddefinitions $end
#0
$dumpvars
b0 U
b0 T
bx S
b1 R
b1 Q
b0 P
b1 O
b1 N
b0 M
bx L
bx K
bx J
b0 I
b0 H
b0 G
b0 F
b0 E
b0 D
b0 C
b0 B
b1000 A
b0 @
b0 ?
b1 >
b0 =
b1 <
b0 ;
b0 :
b1000 9
bx 8
b0 7
b1000 6
bx 5
b1 4
13
12
11
bx 0
x/
b1000 .
1-
b1000 ,
bx +
1*
1)
1(
x'
1&
1%
1$
b1000 #
bx "
x!
$end
#500
0)
0-
0(
0*
#1000
b1010 =
b1010 G
b1010 U
bx :
bx D
bx H
b101000 #
b101000 ,
b101000 .
b101000 6
b1010 T
b1000010 P
b1 F
b1010 B
b10 4
b10 >
b10 R
b1 ?
b1000010101000 9
b1000010101000 A
b10 <
b10 O
b10 Q
b1 7
b1 @
b1 M
1(
1*
#1500
0(
0*
#2000
b1 =
b1 G
b1 U
b1010 :
b1010 D
b1010 H
b11000 #
b11000 ,
b11000 .
b11000 6
b1 T
b10000000 P
b10 F
b1 B
b11 4
b11 >
b11 R
b10 ?
b10000000011000 9
b10000000011000 A
b11 <
b11 O
b11 Q
b10 7
b10 @
b10 M
1(
1*
#2500
0(
0*
#3000
02
0%
0'
b1001 L
b1001 8
b1001 K
b1001 S
b11 0
b11 "
b11 +
b11 5
b11 J
b1001 =
b1001 G
b1001 U
b1 ;
b1 E
b1 I
b10011 #
b10011 ,
b10011 .
b10011 6
b100001 T
b1001000 P
b1 F
b10 C
b100 4
b100 >
b100 R
b11 ?
b1001000010011 9
b1001000010011 A
b100 <
b100 O
b100 Q
b11 7
b11 @
b11 M
1(
1*
#3500
0(
0*
#4000
03
0&
x'
bx =
bx G
bx U
bx L
bx 8
bx K
bx S
b1001 ;
b1001 E
b1001 I
bx :
bx D
bx H
b1010 #
b1010 ,
b1010 .
b1010 6
b11000 T
b110 P
b0 F
b1 C
b1000 B
b101 4
b101 >
b101 R
b100 ?
b110001010 9
b110001010 A
b101 <
b101 O
b101 Q
b100 7
b100 @
b100 M
1(
1*
#4500
0(
0*
#5000
01
0$
b0 ;
b0 E
b0 I
b1001 #
b1001 ,
b1001 .
b1001 6
b1100 T
b11 P
b0 C
b1100 B
b11 4
b11 >
b11 R
b101 ?
b11001001 9
b11001001 A
b110 <
b110 O
b110 Q
b101 7
b101 @
b101 M
1(
1*
#5500
0(
0*
#6000
11
1$
13
1&
0'
b1000 =
b1000 G
b1000 U
b1000 L
b1000 8
b1000 K
b1000 S
b100 4
b100 >
b100 R
b1 ;
b1 E
b1 I
b1001 :
b1001 D
b1001 H
b10011 #
b10011 ,
b10011 .
b10011 6
b100001 T
b1001000 P
b1 F
b10 C
b1 B
b11 ?
b1001000010011 9
b1001000010011 A
b100 <
b100 O
b100 Q
b11 7
b11 @
b11 M
1(
1*
#6500
0(
0*
#7000
03
0&
x'
bx =
bx G
bx U
bx L
bx 8
bx K
bx S
b1000 ;
b1000 E
b1000 I
bx :
bx D
bx H
b1010 #
b1010 ,
b1010 .
b1010 6
b11000 T
b110 P
b0 F
b1 C
b1000 B
b101 4
b101 >
b101 R
b100 ?
b110001010 9
b110001010 A
b101 <
b101 O
b101 Q
b100 7
b100 @
b100 M
1(
1*
#7500
0(
0*
#8000
01
0$
b0 ;
b0 E
b0 I
b1001 #
b1001 ,
b1001 .
b1001 6
b1100 T
b11 P
b0 C
b1100 B
b11 4
b11 >
b11 R
b101 ?
b11001001 9
b11001001 A
b110 <
b110 O
b110 Q
b101 7
b101 @
b101 M
1(
1*
#8500
0(
0*
#9000
11
1$
13
1&
0'
b111 =
b111 G
b111 U
b111 L
b111 8
b111 K
b111 S
b100 4
b100 >
b100 R
b1 ;
b1 E
b1 I
b1000 :
b1000 D
b1000 H
b10011 #
b10011 ,
b10011 .
b10011 6
b100001 T
b1001000 P
b1 F
b10 C
b1 B
b11 ?
b1001000010011 9
b1001000010011 A
b100 <
b100 O
b100 Q
b11 7
b11 @
b11 M
1(
1*
#9500
0(
0*
#10000
03
0&
x'
bx =
bx G
bx U
bx L
bx 8
bx K
bx S
b111 ;
b111 E
b111 I
bx :
bx D
bx H
b1010 #
b1010 ,
b1010 .
b1010 6
b11000 T
b110 P
b0 F
b1 C
b1000 B
b101 4
b101 >
b101 R
b100 ?
b110001010 9
b110001010 A
b101 <
b101 O
b101 Q
b100 7
b100 @
b100 M
1(
1*
#10500
0(
0*
#11000
01
0$
b0 ;
b0 E
b0 I
b1001 #
b1001 ,
b1001 .
b1001 6
b1100 T
b11 P
b0 C
b1100 B
b11 4
b11 >
b11 R
b101 ?
b11001001 9
b11001001 A
b110 <
b110 O
b110 Q
b101 7
b101 @
b101 M
1(
1*
#11500
0(
0*
#12000
11
1$
13
1&
0'
b110 =
b110 G
b110 U
b110 L
b110 8
b110 K
b110 S
b100 4
b100 >
b100 R
b1 ;
b1 E
b1 I
b111 :
b111 D
b111 H
b10011 #
b10011 ,
b10011 .
b10011 6
b100001 T
b1001000 P
b1 F
b10 C
b1 B
b11 ?
b1001000010011 9
b1001000010011 A
b100 <
b100 O
b100 Q
b11 7
b11 @
b11 M
1(
1*
#12500
0(
0*
#13000
03
0&
x'
bx =
bx G
bx U
bx L
bx 8
bx K
bx S
b110 ;
b110 E
b110 I
bx :
bx D
bx H
b1010 #
b1010 ,
b1010 .
b1010 6
b11000 T
b110 P
b0 F
b1 C
b1000 B
b101 4
b101 >
b101 R
b100 ?
b110001010 9
b110001010 A
b101 <
b101 O
b101 Q
b100 7
b100 @
b100 M
1(
1*
#13500
0(
0*
#14000
01
0$
b0 ;
b0 E
b0 I
b1001 #
b1001 ,
b1001 .
b1001 6
b1100 T
b11 P
b0 C
b1100 B
b11 4
b11 >
b11 R
b101 ?
b11001001 9
b11001001 A
b110 <
b110 O
b110 Q
b101 7
b101 @
b101 M
1(
1*
#14500
0(
0*
#15000
11
1$
13
1&
0'
b101 =
b101 G
b101 U
b101 L
b101 8
b101 K
b101 S
b100 4
b100 >
b100 R
b1 ;
b1 E
b1 I
b110 :
b110 D
b110 H
b10011 #
b10011 ,
b10011 .
b10011 6
b100001 T
b1001000 P
b1 F
b10 C
b1 B
b11 ?
b1001000010011 9
b1001000010011 A
b100 <
b100 O
b100 Q
b11 7
b11 @
b11 M
1(
1*
#15500
0(
0*
#16000
03
0&
x'
bx =
bx G
bx U
bx L
bx 8
bx K
bx S
b101 ;
b101 E
b101 I
bx :
bx D
bx H
b1010 #
b1010 ,
b1010 .
b1010 6
b11000 T
b110 P
b0 F
b1 C
b1000 B
b101 4
b101 >
b101 R
b100 ?
b110001010 9
b110001010 A
b101 <
b101 O
b101 Q
b100 7
b100 @
b100 M
1(
1*
#16500
0(
0*
#17000
01
0$
b0 ;
b0 E
b0 I
b1001 #
b1001 ,
b1001 .
b1001 6
b1100 T
b11 P
b0 C
b1100 B
b11 4
b11 >
b11 R
b101 ?
b11001001 9
b11001001 A
b110 <
b110 O
b110 Q
b101 7
b101 @
b101 M
1(
1*
#17500
0(
0*
#18000
11
1$
13
1&
0'
b100 =
b100 G
b100 U
b100 L
b100 8
b100 K
b100 S
b100 4
b100 >
b100 R
b1 ;
b1 E
b1 I
b101 :
b101 D
b101 H
b10011 #
b10011 ,
b10011 .
b10011 6
b100001 T
b1001000 P
b1 F
b10 C
b1 B
b11 ?
b1001000010011 9
b1001000010011 A
b100 <
b100 O
b100 Q
b11 7
b11 @
b11 M
1(
1*
#18500
0(
0*
#19000
03
0&
x'
bx =
bx G
bx U
bx L
bx 8
bx K
bx S
b100 ;
b100 E
b100 I
bx :
bx D
bx H
b1010 #
b1010 ,
b1010 .
b1010 6
b11000 T
b110 P
b0 F
b1 C
b1000 B
b101 4
b101 >
b101 R
b100 ?
b110001010 9
b110001010 A
b101 <
b101 O
b101 Q
b100 7
b100 @
b100 M
1(
1*
#19500
0(
0*
#20000
01
0$
b0 ;
b0 E
b0 I
b1001 #
b1001 ,
b1001 .
b1001 6
b1100 T
b11 P
b0 C
b1100 B
b11 4
b11 >
b11 R
b101 ?
b11001001 9
b11001001 A
b110 <
b110 O
b110 Q
b101 7
b101 @
b101 M
1(
1*
#20500
0(
0*
#21000
11
1$
13
1&
0'
b11 =
b11 G
b11 U
b11 L
b11 8
b11 K
b11 S
b100 4
b100 >
b100 R
b1 ;
b1 E
b1 I
b100 :
b100 D
b100 H
b10011 #
b10011 ,
b10011 .
b10011 6
b100001 T
b1001000 P
b1 F
b10 C
b1 B
b11 ?
b1001000010011 9
b1001000010011 A
b100 <
b100 O
b100 Q
b11 7
b11 @
b11 M
1(
1*
#21500
0(
0*
#22000
03
0&
x'
bx =
bx G
bx U
bx L
bx 8
bx K
bx S
b11 ;
b11 E
b11 I
bx :
bx D
bx H
b1010 #
b1010 ,
b1010 .
b1010 6
b11000 T
b110 P
b0 F
b1 C
b1000 B
b101 4
b101 >
b101 R
b100 ?
b110001010 9
b110001010 A
b101 <
b101 O
b101 Q
b100 7
b100 @
b100 M
1(
1*
#22500
0(
0*
#23000
01
0$
b0 ;
b0 E
b0 I
b1001 #
b1001 ,
b1001 .
b1001 6
b1100 T
b11 P
b0 C
b1100 B
b11 4
b11 >
b11 R
b101 ?
b11001001 9
b11001001 A
b110 <
b110 O
b110 Q
b101 7
b101 @
b101 M
1(
1*
#23500
0(
0*
#24000
11
1$
13
1&
0'
b10 =
b10 G
b10 U
b10 L
b10 8
b10 K
b10 S
b100 4
b100 >
b100 R
b1 ;
b1 E
b1 I
b11 :
b11 D
b11 H
b10011 #
b10011 ,
b10011 .
b10011 6
b100001 T
b1001000 P
b1 F
b10 C
b1 B
b11 ?
b1001000010011 9
b1001000010011 A
b100 <
b100 O
b100 Q
b11 7
b11 @
b11 M
1(
1*
#24500
0(
0*
#25000
03
0&
x'
bx =
bx G
bx U
bx L
bx 8
bx K
bx S
b10 ;
b10 E
b10 I
bx :
bx D
bx H
b1010 #
b1010 ,
b1010 .
b1010 6
b11000 T
b110 P
b0 F
b1 C
b1000 B
b101 4
b101 >
b101 R
b100 ?
b110001010 9
b110001010 A
b101 <
b101 O
b101 Q
b100 7
b100 @
b100 M
1(
1*
#25500
0(
0*
#26000
01
0$
b0 ;
b0 E
b0 I
b1001 #
b1001 ,
b1001 .
b1001 6
b1100 T
b11 P
b0 C
b1100 B
b11 4
b11 >
b11 R
b101 ?
b11001001 9
b11001001 A
b110 <
b110 O
b110 Q
b101 7
b101 @
b101 M
1(
1*
#26500
0(
0*
#27000
11
1$
13
1&
0'
b1 =
b1 G
b1 U
b1 L
b1 8
b1 K
b1 S
b100 4
b100 >
b100 R
b1 ;
b1 E
b1 I
b10 :
b10 D
b10 H
b10011 #
b10011 ,
b10011 .
b10011 6
b100001 T
b1001000 P
b1 F
b10 C
b1 B
b11 ?
b1001000010011 9
b1001000010011 A
b100 <
b100 O
b100 Q
b11 7
b11 @
b11 M
1(
1*
#27500
0(
0*
#28000
03
0&
x'
bx =
bx G
bx U
bx L
bx 8
bx K
bx S
bx :
bx D
bx H
b1010 #
b1010 ,
b1010 .
b1010 6
b11000 T
b110 P
b0 F
b1 C
b1000 B
b101 4
b101 >
b101 R
b100 ?
b110001010 9
b110001010 A
b101 <
b101 O
b101 Q
b100 7
b100 @
b100 M
1(
1*
#28500
0(
0*
#29000
01
0$
b0 ;
b0 E
b0 I
b1001 #
b1001 ,
b1001 .
b1001 6
b1100 T
b11 P
b0 C
b1100 B
b11 4
b11 >
b11 R
b101 ?
b11001001 9
b11001001 A
b110 <
b110 O
b110 Q
b101 7
b101 @
b101 M
1(
1*
#29500
0(
0*
#30000
11
1$
13
1&
1'
b0 =
b0 G
b0 U
b0 L
b0 8
b0 K
b0 S
b100 4
b100 >
b100 R
b1 ;
b1 E
b1 I
b1 :
b1 D
b1 H
b10011 #
b10011 ,
b10011 .
b10011 6
b100001 T
b1001000 P
b1 F
b10 C
b1 B
b11 ?
b1001000010011 9
b1001000010011 A
b100 <
b100 O
b100 Q
b11 7
b11 @
b11 M
1(
1*
#30500
0(
0*
#31000
11
1$
03
0&
x'
bx =
bx G
bx U
bx L
bx 8
bx K
bx S
b0 ;
b0 E
b0 I
bx :
bx D
bx H
b1010 #
b1010 ,
b1010 .
b1010 6
b11000 T
b110 P
b0 F
b1 C
b1000 B
b101 4
b101 >
b101 R
b100 ?
b110001010 9
b110001010 A
b101 <
b101 O
b101 Q
b100 7
b100 @
b100 M
1(
1*
#31500
0(
0*
#32000
01
0$
b1001 #
b1001 ,
b1001 .
b1001 6
b1100 T
b11 P
b0 C
b1100 B
b11 4
b11 >
b11 R
b101 ?
b11001001 9
b11001001 A
b110 <
b110 O
b110 Q
b101 7
b101 @
b101 M
1(
1*
#32500
0(
0*
#33000
11
1$
13
1&
0'
b11111111 =
b11111111 G
b11111111 U
b11111111 L
b11111111 8
b11111111 K
b11111111 S
b100 4
b100 >
b100 R
b1 ;
b1 E
b1 I
b0 :
b0 D
b0 H
b10011 #
b10011 ,
b10011 .
b10011 6
b100001 T
b1001000 P
b1 F
b10 C
b1 B
b11 ?
b1001000010011 9
b1001000010011 A
b100 <
b100 O
b100 Q
b11 7
b11 @
b11 M
1(
1*
#33500
0(
0*
#34000
03
0&
x'
bx =
bx G
bx U
bx L
bx 8
bx K
bx S
b11111111 ;
b11111111 E
b11111111 I
bx :
bx D
bx H
b1010 #
b1010 ,
b1010 .
b1010 6
b11000 T
b110 P
b0 F
b1 C
b1000 B
b101 4
b101 >
b101 R
b100 ?
b110001010 9
b110001010 A
b101 <
b101 O
b101 Q
b100 7
b100 @
b100 M
1(
1*
#34500
0(
0*
#35000
01
0$
b0 ;
b0 E
b0 I
b1001 #
b1001 ,
b1001 .
b1001 6
b1100 T
b11 P
b0 C
b1100 B
b11 4
b11 >
b11 R
b101 ?
b11001001 9
b11001001 A
b110 <
b110 O
b110 Q
b101 7
b101 @
b101 M
1(
1*
#35500
0(
0*
#36000
11
1$
13
1&
0'
b11111110 =
b11111110 G
b11111110 U
b11111110 L
b11111110 8
b11111110 K
b11111110 S
b100 4
b100 >
b100 R
b1 ;
b1 E
b1 I
b11111111 :
b11111111 D
b11111111 H
b10011 #
b10011 ,
b10011 .
b10011 6
b100001 T
b1001000 P
b1 F
b10 C
b1 B
b11 ?
b1001000010011 9
b1001000010011 A
b100 <
b100 O
b100 Q
b11 7
b11 @
b11 M
1(
1*
#36500
0(
0*
#37000
03
0&
x'
bx =
bx G
bx U
bx L
bx 8
bx K
bx S
b11111110 ;
b11111110 E
b11111110 I
bx :
bx D
bx H
b1010 #
b1010 ,
b1010 .
b1010 6
b11000 T
b110 P
b0 F
b1 C
b1000 B
b101 4
b101 >
b101 R
b100 ?
b110001010 9
b110001010 A
b101 <
b101 O
b101 Q
b100 7
b100 @
b100 M
1(
1*
#37500
0(
0*
#38000
01
0$
b0 ;
b0 E
b0 I
b1001 #
b1001 ,
b1001 .
b1001 6
b1100 T
b11 P
b0 C
b1100 B
b11 4
b11 >
b11 R
b101 ?
b11001001 9
b11001001 A
b110 <
b110 O
b110 Q
b101 7
b101 @
b101 M
1(
1*
#38500
0(
0*
#39000
11
1$
13
1&
0'
b11111101 =
b11111101 G
b11111101 U
b11111101 L
b11111101 8
b11111101 K
b11111101 S
b100 4
b100 >
b100 R
b1 ;
b1 E
b1 I
b11111110 :
b11111110 D
b11111110 H
b10011 #
b10011 ,
b10011 .
b10011 6
b100001 T
b1001000 P
b1 F
b10 C
b1 B
b11 ?
b1001000010011 9
b1001000010011 A
b100 <
b100 O
b100 Q
b11 7
b11 @
b11 M
1(
1*
#39500
0(
0*
#40000
03
0&
x'
bx =
bx G
bx U
bx L
bx 8
bx K
bx S
b11111101 ;
b11111101 E
b11111101 I
bx :
bx D
bx H
b1010 #
b1010 ,
b1010 .
b1010 6
b11000 T
b110 P
b0 F
b1 C
b1000 B
b101 4
b101 >
b101 R
b100 ?
b110001010 9
b110001010 A
b101 <
b101 O
b101 Q
b100 7
b100 @
b100 M
1(
1*
#40500
0(
0*
#41000
01
0$
b0 ;
b0 E
b0 I
b1001 #
b1001 ,
b1001 .
b1001 6
b1100 T
b11 P
b0 C
b1100 B
b11 4
b11 >
b11 R
b101 ?
b11001001 9
b11001001 A
b110 <
b110 O
b110 Q
b101 7
b101 @
b101 M
1(
1*
#41500
0(
0*
#42000
11
1$
13
1&
0'
b11111100 =
b11111100 G
b11111100 U
b11111100 L
b11111100 8
b11111100 K
b11111100 S
b100 4
b100 >
b100 R
b1 ;
b1 E
b1 I
b11111101 :
b11111101 D
b11111101 H
b10011 #
b10011 ,
b10011 .
b10011 6
b100001 T
b1001000 P
b1 F
b10 C
b1 B
b11 ?
b1001000010011 9
b1001000010011 A
b100 <
b100 O
b100 Q
b11 7
b11 @
b11 M
1(
1*
#42500
0(
0*
#43000
03
0&
x'
bx =
bx G
bx U
bx L
bx 8
bx K
bx S
b11111100 ;
b11111100 E
b11111100 I
bx :
bx D
bx H
b1010 #
b1010 ,
b1010 .
b1010 6
b11000 T
b110 P
b0 F
b1 C
b1000 B
b101 4
b101 >
b101 R
b100 ?
b110001010 9
b110001010 A
b101 <
b101 O
b101 Q
b100 7
b100 @
b100 M
1(
1*
#43500
0(
0*
#44000
01
0$
b0 ;
b0 E
b0 I
b1001 #
b1001 ,
b1001 .
b1001 6
b1100 T
b11 P
b0 C
b1100 B
b11 4
b11 >
b11 R
b101 ?
b11001001 9
b11001001 A
b110 <
b110 O
b110 Q
b101 7
b101 @
b101 M
1(
1*
#44500
0(
0*
#45000
11
1$
13
1&
0'
b11111011 =
b11111011 G
b11111011 U
b11111011 L
b11111011 8
b11111011 K
b11111011 S
b100 4
b100 >
b100 R
b1 ;
b1 E
b1 I
b11111100 :
b11111100 D
b11111100 H
b10011 #
b10011 ,
b10011 .
b10011 6
b100001 T
b1001000 P
b1 F
b10 C
b1 B
b11 ?
b1001000010011 9
b1001000010011 A
b100 <
b100 O
b100 Q
b11 7
b11 @
b11 M
1(
1*
#45500
0(
0*
#46000
03
0&
x'
bx =
bx G
bx U
bx L
bx 8
bx K
bx S
b11111011 ;
b11111011 E
b11111011 I
bx :
bx D
bx H
b1010 #
b1010 ,
b1010 .
b1010 6
b11000 T
b110 P
b0 F
b1 C
b1000 B
b101 4
b101 >
b101 R
b100 ?
b110001010 9
b110001010 A
b101 <
b101 O
b101 Q
b100 7
b100 @
b100 M
1(
1*
#46500
0(
0*
#47000
01
0$
b0 ;
b0 E
b0 I
b1001 #
b1001 ,
b1001 .
b1001 6
b1100 T
b11 P
b0 C
b1100 B
b11 4
b11 >
b11 R
b101 ?
b11001001 9
b11001001 A
b110 <
b110 O
b110 Q
b101 7
b101 @
b101 M
1(
1*
#47500
0(
0*
#48000
11
1$
13
1&
0'
b11111010 =
b11111010 G
b11111010 U
b11111010 L
b11111010 8
b11111010 K
b11111010 S
b100 4
b100 >
b100 R
b1 ;
b1 E
b1 I
b11111011 :
b11111011 D
b11111011 H
b10011 #
b10011 ,
b10011 .
b10011 6
b100001 T
b1001000 P
b1 F
b10 C
b1 B
b11 ?
b1001000010011 9
b1001000010011 A
b100 <
b100 O
b100 Q
b11 7
b11 @
b11 M
1(
1*
#48500
0(
0*
#49000
03
0&
x'
bx =
bx G
bx U
bx L
bx 8
bx K
bx S
b11111010 ;
b11111010 E
b11111010 I
bx :
bx D
bx H
b1010 #
b1010 ,
b1010 .
b1010 6
b11000 T
b110 P
b0 F
b1 C
b1000 B
b101 4
b101 >
b101 R
b100 ?
b110001010 9
b110001010 A
b101 <
b101 O
b101 Q
b100 7
b100 @
b100 M
1(
1*
#49500
0(
0*
#50000
01
0$
b0 ;
b0 E
b0 I
b1001 #
b1001 ,
b1001 .
b1001 6
b1100 T
b11 P
b0 C
b1100 B
b11 4
b11 >
b11 R
b101 ?
b11001001 9
b11001001 A
b110 <
b110 O
b110 Q
b101 7
b101 @
b101 M
1(
1*
#50500
0(
0*
#51000
11
1$
13
1&
0'
b11111001 =
b11111001 G
b11111001 U
b11111001 L
b11111001 8
b11111001 K
b11111001 S
b100 4
b100 >
b100 R
b1 ;
b1 E
b1 I
b11111010 :
b11111010 D
b11111010 H
b10011 #
b10011 ,
b10011 .
b10011 6
b100001 T
b1001000 P
b1 F
b10 C
b1 B
b11 ?
b1001000010011 9
b1001000010011 A
b100 <
b100 O
b100 Q
b11 7
b11 @
b11 M
1(
1*
#51500
0(
0*
